{
  "version": "6.6.4",
  "objects": [
    {
      "rx": 0,
      "ry": 0,
      "padding": 10,
      "fill": "#F2F2F2",
      "selectable": false,
      "evented": true,
      "lockMovementX": false,
      "lockMovementY": false,
      "objectCaching": false,
      "transparentCorners": true,
      "hasBorders": true,
      "globalCompositeOperation": "source-over",
      "type": "Rect",
      "version": "6.6.4",
      "originX": "left",
      "originY": "top",
      "left": 0,
      "top": 0,
      "width": 600,
      "height": 400,
      "stroke": "pink",
      "strokeWidth": 2,
      "strokeDashArray": null,
      "strokeLineCap": "butt",
      "strokeDashOffset": 0,
      "strokeLineJoin": "miter",
      "strokeUniform": false,
      "strokeMiterLimit": 4,
      "scaleX": 1,
      "scaleY": 1,
      "angle": 0,
      "flipX": false,
      "flipY": false,
      "opacity": 1,
      "shadow": null,
      "visible": true,
      "backgroundColor": "",
      "fillRule": "nonzero",
      "paintFirst": "fill",
      "skewX": 0,
      "skewY": 0
    },
    {
      "cropX": 0,
      "cropY": 0,
      "name": "王洋洋",
      "padding": 10,
      "fill": "rgb(0,0,0)",
      "selectable": true,
      "evented": true,
      "lockMovementX": false,
      "lockMovementY": false,
      "objectCaching": false,
      "transparentCorners": true,
      "hasBorders": true,
      "globalCompositeOperation": "source-over",
      "type": "Image",
      "version": "6.6.4",
      "originX": "left",
      "originY": "top",
      "left": 87.9367,
      "top": 39.0131,
      "width": 120,
      "height": 104,
      "stroke": null,
      "strokeWidth": 0,
      "strokeDashArray": null,
      "strokeLineCap": "butt",
      "strokeDashOffset": 0,
      "strokeLineJoin": "miter",
      "strokeUniform": true,
      "strokeMiterLimit": 4,
      "scaleX": 1,
      "scaleY": 1,
      "angle": 0,
      "flipX": false,
      "flipY": false,
      "opacity": 1,
      "shadow": null,
      "visible": true,
      "backgroundColor": "",
      "fillRule": "nonzero",
      "paintFirst": "fill",
      "skewX": 0,
      "skewY": 0,
      "src": "http://localhost:5173/src/components/OfficeEditor/CanvasLeft/assets/desk-no-shadow.svg",
      "crossOrigin": null,
      "filters": []
    },
    {
      "cropX": 0,
      "cropY": 0,
      "name": "胖二龙",
      "padding": 10,
      "fill": "rgb(0,0,0)",
      "selectable": true,
      "evented": true,
      "lockMovementX": false,
      "lockMovementY": false,
      "objectCaching": false,
      "transparentCorners": true,
      "hasBorders": true,
      "globalCompositeOperation": "source-over",
      "type": "Image",
      "version": "6.6.4",
      "originX": "left",
      "originY": "top",
      "left": 87.9367,
      "top": 142.8919,
      "width": 120,
      "height": 104,
      "stroke": null,
      "strokeWidth": 0,
      "strokeDashArray": null,
      "strokeLineCap": "butt",
      "strokeDashOffset": 0,
      "strokeLineJoin": "miter",
      "strokeUniform": true,
      "strokeMiterLimit": 4,
      "scaleX": 1,
      "scaleY": 1,
      "angle": 0,
      "flipX": false,
      "flipY": true,
      "opacity": 1,
      "shadow": null,
      "visible": true,
      "backgroundColor": "",
      "fillRule": "nonzero",
      "paintFirst": "fill",
      "skewX": 0,
      "skewY": 0,
      "src": "http://localhost:5173/src/components/OfficeEditor/CanvasLeft/assets/desk-no-shadow.svg",
      "crossOrigin": null,
      "filters": []
    },
    {
      "cropX": 0,
      "cropY": 0,
      "name": "牛静香",
      "padding": 10,
      "fill": "rgb(0,0,0)",
      "selectable": true,
      "evented": true,
      "lockMovementX": false,
      "lockMovementY": false,
      "objectCaching": false,
      "transparentCorners": true,
      "hasBorders": true,
      "globalCompositeOperation": "source-over",
      "type": "Image",
      "version": "6.6.4",
      "originX": "left",
      "originY": "top",
      "left": 207.8999,
      "top": 39.0131,
      "width": 120,
      "height": 104,
      "stroke": null,
      "strokeWidth": 0,
      "strokeDashArray": null,
      "strokeLineCap": "butt",
      "strokeDashOffset": 0,
      "strokeLineJoin": "miter",
      "strokeUniform": true,
      "strokeMiterLimit": 4,
      "scaleX": 1,
      "scaleY": 1,
      "angle": 0,
      "flipX": false,
      "flipY": false,
      "opacity": 1,
      "shadow": null,
      "visible": true,
      "backgroundColor": "",
      "fillRule": "nonzero",
      "paintFirst": "fill",
      "skewX": 0,
      "skewY": 0,
      "src": "http://localhost:5173/src/components/OfficeEditor/CanvasLeft/assets/desk-no-shadow.svg",
      "crossOrigin": null,
      "filters": []
    },
    {
      "cropX": 0,
      "cropY": 0,
      "name": "大笨熊",
      "padding": 10,
      "fill": "rgb(0,0,0)",
      "selectable": true,
      "evented": true,
      "lockMovementX": false,
      "lockMovementY": false,
      "objectCaching": false,
      "transparentCorners": true,
      "hasBorders": true,
      "globalCompositeOperation": "source-over",
      "type": "Image",
      "version": "6.6.4",
      "originX": "left",
      "originY": "top",
      "left": 207.8349,
      "top": 142.8919,
      "width": 120,
      "height": 104,
      "stroke": null,
      "strokeWidth": 0,
      "strokeDashArray": null,
      "strokeLineCap": "butt",
      "strokeDashOffset": 0,
      "strokeLineJoin": "miter",
      "strokeUniform": true,
      "strokeMiterLimit": 4,
      "scaleX": 1,
      "scaleY": 1,
      "angle": 0,
      "flipX": false,
      "flipY": true,
      "opacity": 1,
      "shadow": null,
      "visible": true,
      "backgroundColor": "",
      "fillRule": "nonzero",
      "paintFirst": "fill",
      "skewX": 0,
      "skewY": 0,
      "src": "http://localhost:5173/src/components/OfficeEditor/CanvasLeft/assets/desk-no-shadow.svg",
      "crossOrigin": null,
      "filters": []
    }
  ]
}
